daft_builder/__init__.py
daft_builder/pgm.py
daft_builder/utils.py
daft_builder-1.0.1.dist-info/LICENSE
daft_builder-1.0.1.dist-info/METADATA
daft_builder-1.0.1.dist-info/WHEEL
daft_builder-1.0.1.dist-info/top_level.txt
daft_builder-1.0.1.dist-info/RECORD
